dar/__init__.py
dar/cli.py
dar/dar.py
dar-0.1.0.dist-info/METADATA
dar-0.1.0.dist-info/RECORD
dar-0.1.0.dist-info/WHEEL
dar-0.1.0.dist-info/entry_points.txt
dar-0.1.0.dist-info/top_level.txt
