Metadata-Version: 1.1
Name: dar
Version: 0.1.0
Summary: Dar is a command line toolbelt for managing different project workflows.
Home-page: https://github.com/alanbato/dar
Author: Alan Velasco
Author-email: alanvelasco.a@gmail.com
License: MIT license
Keywords: dar
Platform: UNKNOWN
Classifier: Development Status :: 2 - Pre-Alpha
Classifier: Intended Audience :: Developers
Classifier: License :: OSI Approved :: MIT License
Classifier: Natural Language :: English
Classifier: Programming Language :: Python :: 2
Classifier: Programming Language :: Python :: 2.7
Classifier: Programming Language :: Python :: 3
Classifier: Programming Language :: Python :: 3.4
Classifier: Programming Language :: Python :: 3.5
Classifier: Programming Language :: Python :: 3.6
